{
	"format_version": "1.8.0",
	"animations": {
		"animation.clump.walk": {
			"loop": true,
			"animation_length": 1,
			"bones": {
				"goop": {
					"position": {
						"0.0": {
							"post": [0, 0, 0],
							"lerp_mode": "catmullrom"
						},
						"0.25": {
							"post": [0, 0, 5],
							"lerp_mode": "catmullrom"
						},
						"0.75": {
							"post": [0, 0, 0],
							"lerp_mode": "catmullrom"
						},
						"1.0": {
							"post": [0, 0, 0],
							"lerp_mode": "catmullrom"
						}
					},
					"scale": {
						"0.0": {
							"post": [1, 1, 1],
							"lerp_mode": "catmullrom"
						},
						"0.25": {
							"post": [1, 1, 1.25],
							"lerp_mode": "catmullrom"
						},
						"0.75": {
							"post": [1, 1, 0.85],
							"lerp_mode": "catmullrom"
						},
						"1.0": {
							"post": [1, 1, 1],
							"lerp_mode": "catmullrom"
						}
					}
				},
				"ground_goop": {
					"position": {
						"0.0": {
							"post": [0, 0, 0],
							"lerp_mode": "catmullrom"
						},
						"0.25": {
							"post": [0, 0, 4],
							"lerp_mode": "catmullrom"
						},
						"0.75": {
							"post": [0, 0, 0],
							"lerp_mode": "catmullrom"
						},
						"1.0": {
							"post": [0, 0, 0],
							"lerp_mode": "catmullrom"
						}
					},
					"scale": {
						"0.0": {
							"post": [1.25, 1, 1],
							"lerp_mode": "catmullrom"
						},
						"0.25": {
							"post": [1.15, 1, 1.25],
							"lerp_mode": "catmullrom"
						},
						"0.75": {
							"post": [1, 1, 1],
							"lerp_mode": "catmullrom"
						},
						"1.0": {
							"post": [1.25, 1, 1],
							"lerp_mode": "catmullrom"
						}
					}
				},
				"main_goop": {
					"scale": {
						"0.0": {
							"post": [1, 1, 1],
							"lerp_mode": "catmullrom"
						},
						"0.25": {
							"post": [1, 1.15, 1],
							"lerp_mode": "catmullrom"
						},
						"0.75": {
							"post": [1, 0.95, 1],
							"lerp_mode": "catmullrom"
						},
						"1.0": {
							"post": [1, 1, 1],
							"lerp_mode": "catmullrom"
						}
					}
				},
				"left_goop_1": {
					"scale": {
						"0.0": {
							"post": [1, 1, 1],
							"lerp_mode": "catmullrom"
						},
						"0.25": {
							"post": [1, 1.15, 1],
							"lerp_mode": "catmullrom"
						},
						"0.75": {
							"post": [1, 0.95, 1],
							"lerp_mode": "catmullrom"
						},
						"1.0": {
							"post": [1, 1, 1],
							"lerp_mode": "catmullrom"
						}
					}
				},
				"left_goop_2": {
					"scale": {
						"0.0": {
							"post": [1, 1, 1],
							"lerp_mode": "catmullrom"
						},
						"0.25": {
							"post": [1, 1.25, 1],
							"lerp_mode": "catmullrom"
						},
						"0.75": {
							"post": [1, 0.95, 1],
							"lerp_mode": "catmullrom"
						},
						"1.0": {
							"post": [1, 1, 1],
							"lerp_mode": "catmullrom"
						}
					}
				},
				"right_goop_1": {
					"scale": {
						"0.0": {
							"post": [1, 1, 1],
							"lerp_mode": "catmullrom"
						},
						"0.25": {
							"post": [1, 1.25, 1],
							"lerp_mode": "catmullrom"
						},
						"0.75": {
							"post": [1, 0.95, 1],
							"lerp_mode": "catmullrom"
						},
						"1.0": {
							"post": [1, 1, 1],
							"lerp_mode": "catmullrom"
						}
					}
				},
				"right_goop_2": {
					"scale": {
						"0.0": {
							"post": [1, 1, 1],
							"lerp_mode": "catmullrom"
						},
						"0.25": {
							"post": [1, 1.15, 1],
							"lerp_mode": "catmullrom"
						},
						"0.75": {
							"post": [1, 0.95, 1],
							"lerp_mode": "catmullrom"
						},
						"1.0": {
							"post": [1, 1, 1],
							"lerp_mode": "catmullrom"
						}
					}
				},
				"dunk_arm_1": {
					"rotation": {
						"0.0": {
							"post": [0, 25, 0],
							"lerp_mode": "catmullrom"
						},
						"0.25": {
							"post": [0, -25, 0],
							"lerp_mode": "catmullrom"
						},
						"0.75": {
							"post": [-10, 5, 0],
							"lerp_mode": "catmullrom"
						},
						"1.0": {
							"post": [0, 25, 0],
							"lerp_mode": "catmullrom"
						}
					},
					"position": {
						"0.0": {
							"post": [0, 0, 0],
							"lerp_mode": "catmullrom"
						},
						"0.25": {
							"post": [0, 0, -2],
							"lerp_mode": "catmullrom"
						},
						"0.75": {
							"post": [0, 0, -2],
							"lerp_mode": "catmullrom"
						},
						"1.0": {
							"post": [0, 0, 0],
							"lerp_mode": "catmullrom"
						}
					}
				},
				"dunk_arm_2": {
					"rotation": {
						"0.0": {
							"post": [0, 0, 0],
							"lerp_mode": "catmullrom"
						},
						"0.25": {
							"post": [5, 0, 0],
							"lerp_mode": "catmullrom"
						},
						"0.75": {
							"post": [-10, 0, 0],
							"lerp_mode": "catmullrom"
						},
						"1.0": {
							"post": [0, 0, 0],
							"lerp_mode": "catmullrom"
						}
					}
				},
				"dunk_arm_3": {
					"rotation": {
						"0.0": {
							"post": [0, 0, 0],
							"lerp_mode": "catmullrom"
						},
						"0.25": {
							"post": [-5, 0, 0],
							"lerp_mode": "catmullrom"
						},
						"0.75": {
							"post": [-20, 0, 0],
							"lerp_mode": "catmullrom"
						},
						"1.0": {
							"post": [0, 0, 0],
							"lerp_mode": "catmullrom"
						}
					}
				},
				"detailed_arm_1": {
					"rotation": {
						"0.0": {
							"post": [-10, 0, 0],
							"lerp_mode": "catmullrom"
						},
						"0.5": {
							"post": [5, 0, 0],
							"lerp_mode": "catmullrom"
						},
						"1.0": {
							"post": [-10, 0, 0],
							"lerp_mode": "catmullrom"
						}
					},
					"position": {
						"0.0": {
							"post": [0, 0, -1.5],
							"lerp_mode": "catmullrom"
						},
						"0.25": {
							"post": [0, 0, 0.5],
							"lerp_mode": "catmullrom"
						},
						"0.75": {
							"post": [0, 0, -3.5],
							"lerp_mode": "catmullrom"
						},
						"1.0": {
							"post": [0, 0, -1.5],
							"lerp_mode": "catmullrom"
						}
					}
				},
				"detailed_arm_2": {
					"rotation": {
						"0.0": {
							"post": [10, 0, 0],
							"lerp_mode": "catmullrom"
						},
						"0.5": {
							"post": [5, 0, 0],
							"lerp_mode": "catmullrom"
						},
						"1.0": {
							"post": [10, 0, 0],
							"lerp_mode": "catmullrom"
						}
					}
				},
				"detailed_arm_3": {
					"rotation": {
						"0.0": {
							"post": [10, 0, 0],
							"lerp_mode": "catmullrom"
						},
						"0.5": {
							"post": [5, 0, 0],
							"lerp_mode": "catmullrom"
						},
						"1.0": {
							"post": [10, 0, 0],
							"lerp_mode": "catmullrom"
						}
					}
				},
				"right_limb_arm_3": {
					"rotation": {
						"0.0": {
							"post": [0, 0, -5],
							"lerp_mode": "catmullrom"
						},
						"0.25": {
							"post": [0, 0, 0],
							"lerp_mode": "catmullrom"
						},
						"0.75": {
							"post": [0, 0, 15],
							"lerp_mode": "catmullrom"
						},
						"1.0": {
							"post": [0, 0, -5],
							"lerp_mode": "catmullrom"
						}
					}
				},
				"right_limb_leg_3": {
					"rotation": {
						"0.0": {
							"post": [0, 0, -10],
							"lerp_mode": "catmullrom"
						},
						"0.25": {
							"post": [0, 0, 0],
							"lerp_mode": "catmullrom"
						},
						"0.75": {
							"post": [0, 0, 15],
							"lerp_mode": "catmullrom"
						},
						"1.0": {
							"post": [0, 0, -10],
							"lerp_mode": "catmullrom"
						}
					}
				},
				"right_limb_leg_4": {
					"rotation": {
						"0.0": {
							"post": [0, 0, 10],
							"lerp_mode": "catmullrom"
						},
						"0.25": {
							"post": [0, 0, 0],
							"lerp_mode": "catmullrom"
						},
						"0.75": {
							"post": [0, 0, 35],
							"lerp_mode": "catmullrom"
						},
						"1.0": {
							"post": [0, 0, 10],
							"lerp_mode": "catmullrom"
						}
					}
				},
				"left_limb_leg_1": {
					"rotation": {
						"0.0": {
							"post": [0, 0, -5],
							"lerp_mode": "catmullrom"
						},
						"0.5": {
							"post": [0, 0, 10],
							"lerp_mode": "catmullrom"
						},
						"1.0": {
							"post": [0, 0, -5],
							"lerp_mode": "catmullrom"
						}
					},
					"position": {
						"0.0": {
							"post": [0, 0, 0],
							"lerp_mode": "catmullrom"
						},
						"0.5": {
							"post": [0, 0, -1],
							"lerp_mode": "catmullrom"
						},
						"1.0": {
							"post": [0, 0, 0],
							"lerp_mode": "catmullrom"
						}
					}
				},
				"left_limb_leg_2": {
					"rotation": {
						"0.0": {
							"post": [0, 0, -5],
							"lerp_mode": "catmullrom"
						},
						"0.5": {
							"post": [0, 0, 10],
							"lerp_mode": "catmullrom"
						},
						"1.0": {
							"post": [0, 0, -5],
							"lerp_mode": "catmullrom"
						}
					}
				},
				"left_limb_leg_3": {
					"rotation": {
						"0.0": {
							"post": [0, 0, -5],
							"lerp_mode": "catmullrom"
						},
						"0.5": {
							"post": [0, 0, 10],
							"lerp_mode": "catmullrom"
						},
						"1.0": {
							"post": [0, 0, -5],
							"lerp_mode": "catmullrom"
						}
					}
				},
				"left_limb_leg_1_1": {
					"rotation": {
						"0.0": {
							"post": [-10, 0, 10],
							"lerp_mode": "catmullrom"
						},
						"0.5": {
							"post": [-12.5, 6.56007, 0.82855],
							"lerp_mode": "catmullrom"
						},
						"1.0": {
							"post": [-10, 0, 10],
							"lerp_mode": "catmullrom"
						}
					},
					"position": {
						"0.0": {
							"post": [0, 0, 0],
							"lerp_mode": "catmullrom"
						},
						"0.25": {
							"post": [0, 0, 4],
							"lerp_mode": "catmullrom"
						},
						"0.75": {
							"post": [0, 0, -2],
							"lerp_mode": "catmullrom"
						},
						"1.0": {
							"post": [0, 0, 0],
							"lerp_mode": "catmullrom"
						}
					}
				},
				"left_limb_leg_1_2": {
					"rotation": {
						"0.0": {
							"post": [0, 0, 10],
							"lerp_mode": "catmullrom"
						},
						"0.5": {
							"post": [0, 0, 5],
							"lerp_mode": "catmullrom"
						},
						"1.0": {
							"post": [0, 0, 10],
							"lerp_mode": "catmullrom"
						}
					}
				},
				"left_limb_leg_1_3": {
					"rotation": {
						"0.0": {
							"post": [0, 0, -10],
							"lerp_mode": "catmullrom"
						},
						"0.5": {
							"post": [0, 0, 5],
							"lerp_mode": "catmullrom"
						},
						"1.0": {
							"post": [0, 0, -10],
							"lerp_mode": "catmullrom"
						}
					}
				},
				"right_limb_leg_1_1": {
					"rotation": {
						"0.0": {
							"post": [0, 0, -5],
							"lerp_mode": "catmullrom"
						},
						"0.5": {
							"post": [0, 0, 10],
							"lerp_mode": "catmullrom"
						},
						"1.0": {
							"post": [0, 0, -5],
							"lerp_mode": "catmullrom"
						}
					},
					"position": {
						"0.0": {
							"post": [0, 0, 0],
							"lerp_mode": "catmullrom"
						},
						"0.5": {
							"post": [0, 0, -1],
							"lerp_mode": "catmullrom"
						},
						"1.0": {
							"post": [0, 0, 0],
							"lerp_mode": "catmullrom"
						}
					}
				},
				"right_limb_leg_1_2": {
					"rotation": {
						"0.0": {
							"post": [0, 0, 10],
							"lerp_mode": "catmullrom"
						},
						"0.5": {
							"post": [0, 0, -5],
							"lerp_mode": "catmullrom"
						},
						"1.0": {
							"post": [0, 0, 10],
							"lerp_mode": "catmullrom"
						}
					}
				},
				"right_limb_leg_1_3": {
					"rotation": {
						"0.0": {
							"post": [0, 0, 10],
							"lerp_mode": "catmullrom"
						},
						"0.5": {
							"post": [0, 0, -5],
							"lerp_mode": "catmullrom"
						},
						"1.0": {
							"post": [0, 0, 10],
							"lerp_mode": "catmullrom"
						}
					}
				},
				"right_limb_arm_1_1": {
					"rotation": {
						"0.0": {
							"post": [0, 5, 0],
							"lerp_mode": "catmullrom"
						},
						"0.5": {
							"post": [0, 0, 0],
							"lerp_mode": "catmullrom"
						},
						"1.0": {
							"post": [0, 5, 0],
							"lerp_mode": "catmullrom"
						}
					},
					"position": {
						"0.0": {
							"post": [0, 0, 0],
							"lerp_mode": "catmullrom"
						},
						"0.5": {
							"post": [0, 0, -1],
							"lerp_mode": "catmullrom"
						},
						"1.0": {
							"post": [0, 0, 0],
							"lerp_mode": "catmullrom"
						}
					}
				},
				"right_limb_arm_1_2": {
					"rotation": {
						"0.0": {
							"post": [0, 5, -10],
							"lerp_mode": "catmullrom"
						},
						"0.5": {
							"post": [0, 0, 5],
							"lerp_mode": "catmullrom"
						},
						"1.0": {
							"post": [0, 5, -10],
							"lerp_mode": "catmullrom"
						}
					}
				},
				"left_limb_arm_1_1": {
					"rotation": {
						"0.0": {
							"post": [0, 0, 10],
							"lerp_mode": "catmullrom"
						},
						"0.5": {
							"post": [0, 0, -5],
							"lerp_mode": "catmullrom"
						},
						"1.0": {
							"post": [0, 0, 10],
							"lerp_mode": "catmullrom"
						}
					},
					"position": {
						"0.0": {
							"post": [0, 0, 0],
							"lerp_mode": "catmullrom"
						},
						"0.5": {
							"post": [0, 0, -1],
							"lerp_mode": "catmullrom"
						},
						"1.0": {
							"post": [0, 0, 0],
							"lerp_mode": "catmullrom"
						}
					}
				},
				"left_limb_arm_1_2": {
					"rotation": {
						"0.0": {
							"post": [0, 0, 15],
							"lerp_mode": "catmullrom"
						},
						"0.5": {
							"post": [0, 0, 5],
							"lerp_mode": "catmullrom"
						},
						"1.0": {
							"post": [0, 0, 15],
							"lerp_mode": "catmullrom"
						}
					}
				},
				"right_limb_arm_2_1": {
					"rotation": {
						"0.0": {
							"post": [0, 10, 0],
							"lerp_mode": "catmullrom"
						},
						"0.5": {
							"post": [0, -5, 0],
							"lerp_mode": "catmullrom"
						},
						"1.0": {
							"post": [0, 10, 0],
							"lerp_mode": "catmullrom"
						}
					},
					"position": {
						"0.0": {
							"post": [0, 0, 0],
							"lerp_mode": "catmullrom"
						},
						"0.25": {
							"post": [0, 0, 0],
							"lerp_mode": "catmullrom"
						},
						"0.75": {
							"post": [0, 0, -3],
							"lerp_mode": "catmullrom"
						},
						"1.0": {
							"post": [0, 0, 0],
							"lerp_mode": "catmullrom"
						}
					}
				},
				"right_limb_arm_2_2": {
					"rotation": {
						"0.0": {
							"post": [0, -10, 0],
							"lerp_mode": "catmullrom"
						},
						"0.5": {
							"post": [0, 5, 0],
							"lerp_mode": "catmullrom"
						},
						"1.0": {
							"post": [0, -10, 0],
							"lerp_mode": "catmullrom"
						}
					}
				},
				"right_limb_arm_2_3": {
					"rotation": {
						"0.0": {
							"post": [0, -10, 0],
							"lerp_mode": "catmullrom"
						},
						"0.5": {
							"post": [0, 5, 0],
							"lerp_mode": "catmullrom"
						},
						"1.0": {
							"post": [0, -10, 0],
							"lerp_mode": "catmullrom"
						}
					}
				},
				"limbs": {
					"position": {
						"0.0": {
							"post": [0, 0, 0],
							"lerp_mode": "catmullrom"
						},
						"0.25": {
							"post": [0, 0, 4],
							"lerp_mode": "catmullrom"
						},
						"0.75": {
							"post": [0, 0, 2],
							"lerp_mode": "catmullrom"
						},
						"1.0": {
							"post": [0, 0, 0],
							"lerp_mode": "catmullrom"
						}
					}
				},
				"right_limb_leg_1": {
					"rotation": {
						"0.0": {
							"post": [0, -5, 0],
							"lerp_mode": "catmullrom"
						},
						"0.25": {
							"post": [0, 37.5, 0],
							"lerp_mode": "catmullrom"
						},
						"0.75": {
							"post": [-11.03287, 14.47751, 15.50409],
							"lerp_mode": "catmullrom"
						},
						"1.0": {
							"post": [0, -5, 0],
							"lerp_mode": "catmullrom"
						}
					},
					"position": {
						"0.0": {
							"post": [0, 0, 0],
							"lerp_mode": "catmullrom"
						},
						"0.25": {
							"post": [0, 0, -2],
							"lerp_mode": "catmullrom"
						},
						"0.75": {
							"post": [0, 0, -2],
							"lerp_mode": "catmullrom"
						},
						"1.0": {
							"post": [0, 0, 0],
							"lerp_mode": "catmullrom"
						}
					}
				},
				"right_limb_arm_1": {
					"rotation": {
						"0.0": {
							"post": [0, -10, 0],
							"lerp_mode": "catmullrom"
						},
						"0.25": {
							"post": [0, 15, 0],
							"lerp_mode": "catmullrom"
						},
						"0.75": {
							"post": [15, 0, 15],
							"lerp_mode": "catmullrom"
						},
						"1.0": {
							"post": [0, -10, 0],
							"lerp_mode": "catmullrom"
						}
					},
					"position": {
						"0.0": {
							"post": [0, 0, 0],
							"lerp_mode": "catmullrom"
						},
						"0.25": {
							"post": [0, 0, 2],
							"lerp_mode": "catmullrom"
						},
						"0.75": {
							"post": [0, 0, -3],
							"lerp_mode": "catmullrom"
						},
						"1.0": {
							"post": [0, 0, 0],
							"lerp_mode": "catmullrom"
						}
					}
				}
			}
		},
		"animation.clump.idle": {
			"loop": true,
			"bones": {
				"goop": {
					"scale": [1, "1.125+math.sin(query.life_time*90)*0.075", 1]
				},
				"ground_goop": {
					"scale": ["1.05+math.sin(query.life_time*90)*0.075", 1, "1.05+math.sin(query.life_time*90)*0.075"]
				},
				"main_goop": {
					"scale": [1, "1.075+math.sin(query.life_time*90)*0.0125", 1]
				},
				"left_goop_1": {
					"scale": [1, "1.0125+math.sin(query.life_time*90)*0.0125", 1]
				},
				"left_goop_2": {
					"scale": [1, "1.0125+math.sin(query.life_time*90)*0.0125", 1]
				},
				"right_goop_1": {
					"scale": [1, "1.0125+math.sin(query.life_time*90)*0.0125", 1]
				},
				"right_goop_2": {
					"scale": [1, "1.0125+math.sin(query.life_time*90)*0.0125", 1]
				},
				"dunk_arm_1": {
					"rotation": ["5+math.sin(query.life_time*90)*5", 0, 0]
				},
				"dunk_arm_2": {
					"rotation": ["-10+math.sin(query.life_time*90)*-5", 0, 0]
				},
				"dunk_arm_3": {
					"rotation": ["5+math.sin(query.life_time*90)*-5", 0, 0]
				},
				"detailed_arm_1": {
					"rotation": ["math.sin(query.life_time*90)*-5", 0, 0]
				},
				"detailed_arm_2": {
					"rotation": ["5+math.sin(query.life_time*90)*5", 0, 0]
				},
				"detailed_arm_3": {
					"rotation": ["5+math.sin(query.life_time*90)*-5", 0, 0]
				},
				"right_limb_arm_3": {
					"rotation": [0, 0, "5+math.sin(query.life_time*90)*5"]
				},
				"right_limb_leg_3": {
					"rotation": [0, 0, "math.sin(query.life_time*90)*15"]
				},
				"right_limb_leg_4": {
					"rotation": [0, 0, "math.sin(query.life_time*90)*-10"]
				},
				"left_limb_leg_1": {
					"rotation": [0, 0, "5+math.sin(query.life_time*90)*5"]
				},
				"left_limb_leg_2": {
					"rotation": [0, 0, "5+math.sin(query.life_time*90)*5"]
				},
				"left_limb_leg_3": {
					"rotation": [0, 0, "5+math.sin(query.life_time*90)*5"]
				},
				"left_limb_leg_1_1": {
					"rotation": ["math.sin(query.life_time*90)*-5", 0, "math.sin(query.life_time*90)*5"]
				},
				"left_limb_leg_1_2": {
					"rotation": [0, 0, "10+math.sin(query.life_time*90)*-5"]
				},
				"left_limb_leg_1_3": {
					"rotation": [0, 0, "5+math.sin(query.life_time*90)*-5"]
				},
				"right_limb_leg_1_1": {
					"rotation": [0, 0, "5+math.sin(query.life_time*90)*-5"]
				},
				"right_limb_leg_1_2": {
					"rotation": [0, 0, "5+math.sin(query.life_time*90)*5"]
				},
				"right_limb_leg_1_3": {
					"rotation": [0, 0, "5+math.sin(query.life_time*90)*5"]
				},
				"right_limb_arm_1_1": {
					"rotation": ["-5+math.sin(query.life_time*90)*5", "math.sin(query.life_time*90)*-5", "5+math.sin(query.life_time*90)*-5"]
				},
				"right_limb_arm_1_2": {
					"rotation": [0, 0, "-5+math.sin(query.life_time*90)*-5"]
				},
				"left_limb_arm_1_1": {
					"rotation": [0, 0, "5+math.sin(query.life_time*90)*5"]
				},
				"left_limb_arm_1_2": {
					"rotation": [0, 0, "5+math.sin(query.life_time*90)*5"]
				},
				"right_limb_arm_2_1": {
					"rotation": [0, "5+math.sin(query.life_time*90)*5", 0]
				},
				"right_limb_arm_2_2": {
					"rotation": [0, "math.sin(query.life_time*90)*-5", 0]
				},
				"right_limb_arm_2_3": {
					"rotation": [0, "5+math.sin(query.life_time*90)*-5", 0]
				},
				"right_limb_leg_1": {
					"rotation": ["5+math.sin(query.life_time*90)*5", 0, "-5+math.sin(query.life_time*90)*-5"]
				},
				"right_limb_arm_1": {
					"rotation": [0, 0, "-5+math.sin(query.life_time*90)*-5"]
				}
			}
		}
	}
}